LICENSE
MANIFEST.in
README.md
RELEASE.md
requirements.txt
setup.cfg
setup.py
tests/test_diarize.py
tests/test_diarize_call_remaining.py
willisapi_client/__init__.py
willisapi_client/__version__.py
willisapi_client/logging_setup.py
willisapi_client/timer.py
willisapi_client/willisapi_client.py
willisapi_client.egg-info/PKG-INFO
willisapi_client.egg-info/SOURCES.txt
willisapi_client.egg-info/dependency_links.txt
willisapi_client.egg-info/not-zip-safe
willisapi_client.egg-info/requires.txt
willisapi_client.egg-info/top_level.txt
willisapi_client/services/__init__.py
willisapi_client/services/api.py
willisapi_client/services/exceptions.py
willisapi_client/services/diarize/__init__.py
willisapi_client/services/diarize/diarize_utils.py
willisapi_client/services/diarize/willisdiarize.py
willisapi_client/services/diarize/willisdiarize_call_remaining.py
willisapi_client/services/metadata/__init__.py
willisapi_client/services/metadata/language_choices.py
willisapi_client/services/metadata/upload.py
willisapi_client/services/metadata/utils.py