Metadata-Version: 2.1
Name: willisapi-client
Version: 1.9.4
Summary: A Python client for willisapi
Home-page: https://github.com/bklynhlth/willsiapi_client
Author: bklynhlth
Author-email: admin@brooklyn.health
License: Apache
Requires-Python: >=3.9
License-File: LICENSE
